dynamic_query_builder/__init__.py
dynamic_query_builder/query_builder.py
dynamic_query_builder/utils.py
dynamic_query_builder-0.1.0.dist-info/licenses/LICENSE
dynamic_query_builder-0.1.0.dist-info/METADATA
dynamic_query_builder-0.1.0.dist-info/WHEEL
dynamic_query_builder-0.1.0.dist-info/top_level.txt
dynamic_query_builder-0.1.0.dist-info/RECORD
