Metadata-Version: 2.4
Name: dynamic-query-builder
Version: 0.1.0
Summary: A dynamic query builder with filtering, pagination, and sorting for SQLAlchemy models.
Author: Md Anisur Rahman
Author-email: anisurrahman14046@gmail.com
Classifier: Programming Language :: Python :: 3
Classifier: License :: OSI Approved :: MIT License
Classifier: Operating System :: OS Independent
Requires-Python: >=3.6
License-File: LICENSE
Requires-Dist: sqlalchemy>=1.4
Requires-Dist: fastapi>=0.68
Requires-Dist: asyncpg
Dynamic: author
Dynamic: author-email
Dynamic: classifier
Dynamic: description
Dynamic: description-content-type
Dynamic: license-file
Dynamic: requires-dist
Dynamic: requires-python
Dynamic: summary
